truto_python_sdk/__init__.py
truto_python_sdk/base_resource.py
truto_python_sdk/dict_to_query_string.py
truto_python_sdk/environment.py
truto_python_sdk/environment_integration.py
truto_python_sdk/environment_unified_model.py
truto_python_sdk/integrated_account.py
truto_python_sdk/integration.py
truto_python_sdk/link_token.py
truto_python_sdk/pagination_result.py
truto_python_sdk/proxy_api.py
truto_python_sdk/sync_job.py
truto_python_sdk/sync_job_cron_trigger.py
truto_python_sdk/sync_job_run.py
truto_python_sdk/team.py
truto_python_sdk/truto_api.py
truto_python_sdk/unified_api.py
truto_python_sdk/unified_model.py
truto_python_sdk/user.py
truto_python_sdk/webhook.py
truto_python_sdk-0.1.2.dist-info/LICENSE
truto_python_sdk-0.1.2.dist-info/METADATA
truto_python_sdk-0.1.2.dist-info/WHEEL
truto_python_sdk-0.1.2.dist-info/RECORD
