Metadata-Version: 2.3
Name: truto-python-sdk
Version: 0.1.2
Summary: Python3 SDK for the Truto API
Author: Roopendra Talekar
Author-email: roopendratalekar@gmail.com
Requires-Python: >=3.12,<4.0
Classifier: Programming Language :: Python :: 3
Classifier: Programming Language :: Python :: 3.12
Classifier: Programming Language :: Python :: 3.13
Requires-Dist: aiohttp (==3.12.14)
Requires-Dist: asyncio (==3.4.3)
Project-URL: Repository, https://github.com/trutohq/truto-python-sdk
